.gitignore
AUTHORS
CHANGELOG.md
LICENSE
MANIFEST.in
README.rst
requirements.txt
setup.py
docs/Makefile
docs/api.rst
docs/conf.py
docs/index.rst
docs/make.bat
docs/tutorial.rst
docs/examples/basic-search.rst
docs/examples/cert-stream.rst
docs/examples/gifcreator.rst
docs/examples/query-summary.rst
shodan/__init__.py
shodan/__main__.py
shodan/client.py
shodan/exception.py
shodan/helpers.py
shodan/stream.py
shodan/threatnet.py
shodan.egg-info/PKG-INFO
shodan.egg-info/SOURCES.txt
shodan.egg-info/dependency_links.txt
shodan.egg-info/entry_points.txt
shodan.egg-info/requires.txt
shodan.egg-info/top_level.txt
shodan/cli/__init__.py
shodan/cli/alert.py
shodan/cli/data.py
shodan/cli/helpers.py
shodan/cli/host.py
shodan/cli/organization.py
shodan/cli/scan.py
shodan/cli/settings.py
shodan/cli/worldmap.py
shodan/cli/converter/__init__.py
shodan/cli/converter/base.py
shodan/cli/converter/csvc.py
shodan/cli/converter/excel.py
shodan/cli/converter/geojson.py
shodan/cli/converter/images.py
shodan/cli/converter/kml.py
tests/__init__.py
tests/test_shodan.py